<?xml version="1.0" encoding="UTF-8"?>
<DescribeImagesResponse xmlns="http://ec2.amazonaws.com/doc/2011-01-01/">
    <requestId>f1193c53-5d0c-4814-9df7-e78160eb1aca</requestId>
    <imagesSet>
        <item>
            <imageId>ami-004e7b74</imageId>
            <imageLocation>polopoly-oracle/oracle11-101019.manifest.xml</imageLocation>
            <imageState>available</imageState>
            <imageOwnerId>299230374258</imageOwnerId>
            <isPublic>false</isPublic>
            <architecture>x86_64</architecture>
            <imageType>machine</imageType>
            <kernelId>aki-3190bb45</kernelId>
            <ramdiskId>ari-3790bb43</ramdiskId>
            <rootDeviceType>instance-store</rootDeviceType>
            <blockDeviceMapping/>
            <virtualizationType>paravirtual</virtualizationType>
            <hypervisor>xen</hypervisor>
        </item>
        <item>
            <imageId>ami-01f7dc75</imageId>
            <imageLocation>polopoly-centos5-temis-node/image-100111.manifest.xml</imageLocation>
            <imageState>available</imageState>
            <imageOwnerId>299230374258</imageOwnerId>
            <isPublic>false</isPublic>
            <architecture>i386</architecture>
            <imageType>machine</imageType>
            <rootDeviceType>instance-store</rootDeviceType>
            <rootDeviceName>/dev/sda1</rootDeviceName>
            <blockDeviceMapping/>
            <virtualizationType>paravirtual</virtualizationType>
            <hypervisor>xen</hypervisor>
        </item>
        <item>
            <imageId>ami-058fa471</imageId>
            <imageLocation>polopoly-centos5-test-node/image-100309.manifest.xml</imageLocation>
            <imageState>available</imageState>
            <imageOwnerId>299230374258</imageOwnerId>
            <isPublic>false</isPublic>
            <architecture>x86_64</architecture>
            <imageType>machine</imageType>
            <kernelId>aki-550d2521</kernelId>
            <rootDeviceType>instance-store</rootDeviceType>
            <rootDeviceName>/dev/sda1</rootDeviceName>
            <blockDeviceMapping/>
            <virtualizationType>paravirtual</virtualizationType>
            <hypervisor>xen</hypervisor>
        </item>
        <item>
            <imageId>ami-09bf947d</imageId>
            <imageLocation>polopoly-centos5-main-node/image-100225.manifest.xml</imageLocation>
            <imageState>available</imageState>
            <imageOwnerId>299230374258</imageOwnerId>
            <isPublic>false</isPublic>
            <architecture>i386</architecture>
            <imageType>machine</imageType>
            <rootDeviceType>instance-store</rootDeviceType>
            <rootDeviceName>/dev/sda1</rootDeviceName>
            <blockDeviceMapping/>
            <virtualizationType>paravirtual</virtualizationType>
            <hypervisor>xen</hypervisor>
        </item>
        <item>
            <imageId>ami-0c587378</imageId>
            <imageLocation>polopoly-centos5-preview-template-node/image-091015.manifest.xml</imageLocation>
            <imageState>available</imageState>
            <imageOwnerId>299230374258</imageOwnerId>
            <isPublic>false</isPublic>
            <architecture>i386</architecture>
            <imageType>machine</imageType>
            <rootDeviceType>instance-store</rootDeviceType>
            <blockDeviceMapping/>
            <virtualizationType>paravirtual</virtualizationType>
            <hypervisor>xen</hypervisor>
        </item>
        <item>
            <imageId>ami-0f62487b</imageId>
            <imageLocation>polopoly-release-preview/image-100406-9-16-0-r56449.manifest.xml</imageLocation>
            <imageState>available</imageState>
            <imageOwnerId>299230374258</imageOwnerId>
            <isPublic>false</isPublic>
            <architecture>i386</architecture>
            <imageType>machine</imageType>
            <rootDeviceType>instance-store</rootDeviceType>
            <rootDeviceName>/dev/sda1</rootDeviceName>
            <blockDeviceMapping/>
            <virtualizationType>paravirtual</virtualizationType>
            <hypervisor>xen</hypervisor>
        </item>
        <item>
            <imageId>ami-10496264</imageId>
            <imageLocation>polopoly-windows2003-test-node/image-090925.manifest.xml</imageLocation>
            <imageState>available</imageState>
            <imageOwnerId>299230374258</imageOwnerId>
            <isPublic>false</isPublic>
            <architecture>x86_64</architecture>
            <imageType>machine</imageType>
            <platform>windows</platform>
            <rootDeviceType>instance-store</rootDeviceType>
            <blockDeviceMapping/>
            <virtualizationType>hvm</virtualizationType>
            <hypervisor>xen</hypervisor>
        </item>
        <item>
            <imageId>ami-11053165</imageId>
            <imageLocation>polopoly-centos5-test-node/image-110204.manifest.xml</imageLocation>
            <imageState>available</imageState>
            <imageOwnerId>299230374258</imageOwnerId>
            <isPublic>false</isPublic>
            <architecture>x86_64</architecture>
            <imageType>machine</imageType>
            <kernelId>aki-550d2521</kernelId>
            <rootDeviceType>instance-store</rootDeviceType>
            <rootDeviceName>/dev/sda1</rootDeviceName>
            <blockDeviceMapping/>
            <virtualizationType>paravirtual</virtualizationType>
            <hypervisor>xen</hypervisor>
        </item>
        <item>
            <imageId>ami-122a0166</imageId>
            <imageLocation>polopoly-bigtest/ec2-front-20091028.1.manifest.xml</imageLocation>
            <imageState>available</imageState>
            <imageOwnerId>299230374258</imageOwnerId>
            <isPublic>false</isPublic>
            <architecture>x86_64</architecture>
            <imageType>machine</imageType>
            <rootDeviceType>instance-store</rootDeviceType>
            <blockDeviceMapping/>
            <virtualizationType>paravirtual</virtualizationType>
            <hypervisor>xen</hypervisor>
        </item>
        <item>
            <imageId>ami-126f5a66</imageId>
            <imageLocation>polopoly-centos5-preview-template-node/image-100930-2.manifest.xml</imageLocation>
            <imageState>available</imageState>
            <imageOwnerId>299230374258</imageOwnerId>
            <isPublic>false</isPublic>
            <architecture>i386</architecture>
            <imageType>machine</imageType>
            <rootDeviceType>instance-store</rootDeviceType>
            <rootDeviceName>/dev/sda1</rootDeviceName>
            <blockDeviceMapping/>
            <virtualizationType>paravirtual</virtualizationType>
            <hypervisor>xen</hypervisor>
        </item>
        <item>
            <imageId>ami-1a2a016e</imageId>
            <imageLocation>polopoly-bigtest/ec2-jmeter-node-20091028.manifest.xml</imageLocation>
            <imageState>available</imageState>
            <imageOwnerId>299230374258</imageOwnerId>
            <isPublic>false</isPublic>
            <architecture>i386</architecture>
            <imageType>machine</imageType>
            <rootDeviceType>instance-store</rootDeviceType>
            <blockDeviceMapping/>
            <virtualizationType>paravirtual</virtualizationType>
            <hypervisor>xen</hypervisor>
        </item>
        <item>
            <imageId>ami-1dc6ed69</imageId>
            <imageLocation>polopoly-bigtest-jmeter/image-100125.manifest.xml</imageLocation>
            <imageState>available</imageState>
            <imageOwnerId>299230374258</imageOwnerId>
            <isPublic>false</isPublic>
            <architecture>i386</architecture>
            <imageType>machine</imageType>
            <rootDeviceType>instance-store</rootDeviceType>
            <rootDeviceName>/dev/sda1</rootDeviceName>
            <blockDeviceMapping/>
            <virtualizationType>paravirtual</virtualizationType>
            <hypervisor>xen</hypervisor>
        </item>
        <item>
            <imageId>ami-23e6d357</imageId>
            <imageLocation>polopoly-centos5-test-node/image-101125.manifest.xml</imageLocation>
            <imageState>available</imageState>
            <imageOwnerId>299230374258</imageOwnerId>
            <isPublic>false</isPublic>
            <architecture>x86_64</architecture>
            <imageType>machine</imageType>
            <kernelId>aki-550d2521</kernelId>
            <rootDeviceType>instance-store</rootDeviceType>
            <rootDeviceName>/dev/sda1</rootDeviceName>
            <blockDeviceMapping/>
            <virtualizationType>paravirtual</virtualizationType>
            <hypervisor>xen</hypervisor>
        </item>
        <item>
            <imageId>ami-242f0450</imageId>
            <imageLocation>polopoly-centos5-test-node/image-091030.manifest.xml</imageLocation>
            <imageState>available</imageState>
            <imageOwnerId>299230374258</imageOwnerId>
            <isPublic>false</isPublic>
            <architecture>x86_64</architecture>
            <imageType>machine</imageType>
            <rootDeviceType>instance-store</rootDeviceType>
            <blockDeviceMapping/>
            <virtualizationType>paravirtual</virtualizationType>
            <hypervisor>xen</hypervisor>
        </item>
        <item>
            <imageId>ami-2590a551</imageId>
            <imageLocation>polopoly-release-preview/image-101227-10-0-0-r58402.manifest.xml</imageLocation>
            <imageState>available</imageState>
            <imageOwnerId>299230374258</imageOwnerId>
            <isPublic>false</isPublic>
            <architecture>i386</architecture>
            <imageType>machine</imageType>
            <rootDeviceType>instance-store</rootDeviceType>
            <rootDeviceName>/dev/sda1</rootDeviceName>
            <blockDeviceMapping/>
            <virtualizationType>paravirtual</virtualizationType>
            <hypervisor>xen</hypervisor>
        </item>
        <item>
            <imageId>ami-262a0152</imageId>
            <imageLocation>polopoly-bigtest/ec2-front-20091028.manifest.xml</imageLocation>
            <imageState>available</imageState>
            <imageOwnerId>299230374258</imageOwnerId>
            <isPublic>false</isPublic>
            <architecture>x86_64</architecture>
            <imageType>machine</imageType>
            <rootDeviceType>instance-store</rootDeviceType>
            <blockDeviceMapping/>
            <virtualizationType>paravirtual</virtualizationType>
            <hypervisor>xen</hypervisor>
        </item>
        <item>
            <imageId>ami-26597252</imageId>
            <imageLocation>polopoly-release-preview/image-091014.manifest.xml</imageLocation>
            <imageState>available</imageState>
            <imageOwnerId>299230374258</imageOwnerId>
            <isPublic>false</isPublic>
            <architecture>i386</architecture>
            <imageType>machine</imageType>
            <rootDeviceType>instance-store</rootDeviceType>
            <blockDeviceMapping/>
            <virtualizationType>paravirtual</virtualizationType>
            <hypervisor>xen</hypervisor>
        </item>
        <item>
            <imageId>ami-300e3b44</imageId>
            <imageLocation>299230374258/large-image-test</imageLocation>
            <imageState>available</imageState>
            <imageOwnerId>299230374258</imageOwnerId>
            <isPublic>false</isPublic>
            <architecture>x86_64</architecture>
            <imageType>machine</imageType>
            <kernelId>aki-4feec43b</kernelId>
            <name>large-image-test</name>
            <rootDeviceType>ebs</rootDeviceType>
            <rootDeviceName>/dev/sda1</rootDeviceName>
            <blockDeviceMapping>
                <item>
                    <deviceName>/dev/sda1</deviceName>
                    <ebs>
                        <snapshotId>snap-ce13ada7</snapshotId>
                        <volumeSize>10</volumeSize>
                        <deleteOnTermination>true</deleteOnTermination>
                    </ebs>
                </item>
            </blockDeviceMapping>
            <virtualizationType>paravirtual</virtualizationType>
            <hypervisor>xen</hypervisor>
        </item>
        <item>
            <imageId>ami-31b19a45</imageId>
            <imageLocation>polopoly-centos5-test-node/image-100302.manifest.xml</imageLocation>
            <imageState>available</imageState>
            <imageOwnerId>299230374258</imageOwnerId>
            <isPublic>false</isPublic>
            <architecture>x86_64</architecture>
            <imageType>machine</imageType>
            <kernelId>aki-550d2521</kernelId>
            <rootDeviceType>instance-store</rootDeviceType>
            <rootDeviceName>/dev/sda1</rootDeviceName>
            <blockDeviceMapping/>
            <virtualizationType>paravirtual</virtualizationType>
            <hypervisor>xen</hypervisor>
        </item>
        <item>
            <imageId>ami-345a7140</imageId>
            <imageLocation>polopoly-centos5-preview-template-node/image-091013.manifest.xml</imageLocation>
            <imageState>available</imageState>
            <imageOwnerId>299230374258</imageOwnerId>
            <isPublic>false</isPublic>
            <architecture>i386</architecture>
            <imageType>machine</imageType>
            <rootDeviceType>instance-store</rootDeviceType>
            <blockDeviceMapping/>
            <virtualizationType>paravirtual</virtualizationType>
            <hypervisor>xen</hypervisor>
        </item>
        <item>
            <imageId>ami-350e2541</imageId>
            <imageLocation>polopoly-bigtest/image-091124.manifest.xml</imageLocation>
            <imageState>available</imageState>
            <imageOwnerId>299230374258</imageOwnerId>
            <isPublic>false</isPublic>
            <architecture>x86_64</architecture>
            <imageType>machine</imageType>
            <rootDeviceType>instance-store</rootDeviceType>
            <rootDeviceName>/dev/sda1</rootDeviceName>
            <blockDeviceMapping/>
            <virtualizationType>paravirtual</virtualizationType>
            <hypervisor>xen</hypervisor>
        </item>
        <item>
            <imageId>ami-37c5ee43</imageId>
            <imageLocation>polopoly-release-preview/image-100126-9-15-DR4-r55989.manifest.xml</imageLocation>
            <imageState>available</imageState>
            <imageOwnerId>299230374258</imageOwnerId>
            <isPublic>false</isPublic>
            <architecture>i386</architecture>
            <imageType>machine</imageType>
            <rootDeviceType>instance-store</rootDeviceType>
            <rootDeviceName>/dev/sda1</rootDeviceName>
            <blockDeviceMapping/>
            <virtualizationType>paravirtual</virtualizationType>
            <hypervisor>xen</hypervisor>
        </item>
        <item>
            <imageId>ami-39d6fd4d</imageId>
            <imageLocation>polopoly-centos5-test-node/image-100209.manifest.xml</imageLocation>
            <imageState>available</imageState>
            <imageOwnerId>299230374258</imageOwnerId>
            <isPublic>false</isPublic>
            <architecture>x86_64</architecture>
            <imageType>machine</imageType>
            <kernelId>aki-550d2521</kernelId>
            <rootDeviceType>instance-store</rootDeviceType>
            <rootDeviceName>/dev/sda1</rootDeviceName>
            <blockDeviceMapping/>
            <virtualizationType>paravirtual</virtualizationType>
            <hypervisor>xen</hypervisor>
        </item>
        <item>
            <imageId>ami-3a45704e</imageId>
            <imageLocation>polopoly-centos5-test-node/image-101012-2.manifest.xml</imageLocation>
            <imageState>available</imageState>
            <imageOwnerId>299230374258</imageOwnerId>
            <isPublic>false</isPublic>
            <architecture>x86_64</architecture>
            <imageType>machine</imageType>
            <kernelId>aki-550d2521</kernelId>
            <rootDeviceType>instance-store</rootDeviceType>
            <rootDeviceName>/dev/sda1</rootDeviceName>
            <blockDeviceMapping/>
            <virtualizationType>paravirtual</virtualizationType>
            <hypervisor>xen</hypervisor>
        </item>
        <item>
            <imageId>ami-3a5f744e</imageId>
            <imageLocation>polopoly-release-preview/image-091016-9-15-DR1-r55248.manifest.xml</imageLocation>
            <imageState>available</imageState>
            <imageOwnerId>299230374258</imageOwnerId>
            <isPublic>false</isPublic>
            <architecture>i386</architecture>
            <imageType>machine</imageType>
            <rootDeviceType>instance-store</rootDeviceType>
            <blockDeviceMapping/>
            <virtualizationType>paravirtual</virtualizationType>
            <hypervisor>xen</hypervisor>
        </item>
        <item>
            <imageId>ami-3bb8934f</imageId>
            <imageLocation>polopoly-centos5-test-node/image-100224-2.manifest.xml</imageLocation>
            <imageState>available</imageState>
            <imageOwnerId>299230374258</imageOwnerId>
            <isPublic>false</isPublic>
            <architecture>x86_64</architecture>
            <imageType>machine</imageType>
            <kernelId>aki-550d2521</kernelId>
            <rootDeviceType>instance-store</rootDeviceType>
            <rootDeviceName>/dev/sda1</rootDeviceName>
            <blockDeviceMapping/>
            <virtualizationType>paravirtual</virtualizationType>
            <hypervisor>xen</hypervisor>
        </item>
        <item>
            <imageId>ami-3deac049</imageId>
            <imageLocation>polopoly-release-preview/image-100628-9-17-DR3-r57131.manifest.xml</imageLocation>
            <imageState>available</imageState>
            <imageOwnerId>299230374258</imageOwnerId>
            <isPublic>false</isPublic>
            <architecture>i386</architecture>
            <imageType>machine</imageType>
            <rootDeviceType>instance-store</rootDeviceType>
            <rootDeviceName>/dev/sda1</rootDeviceName>
            <blockDeviceMapping/>
            <virtualizationType>paravirtual</virtualizationType>
            <hypervisor>xen</hypervisor>
        </item>
        <item>
            <imageId>ami-3f32184b</imageId>
            <imageLocation>polopoly-release-preview/image-100601-9-16-1-r56882.manifest.xml</imageLocation>
            <imageState>available</imageState>
            <imageOwnerId>299230374258</imageOwnerId>
            <isPublic>false</isPublic>
            <architecture>i386</architecture>
            <imageType>machine</imageType>
            <rootDeviceType>instance-store</rootDeviceType>
            <rootDeviceName>/dev/sda1</rootDeviceName>
            <blockDeviceMapping/>
            <virtualizationType>paravirtual</virtualizationType>
            <hypervisor>xen</hypervisor>
        </item>
        <item>
            <imageId>ami-3f380c4b</imageId>
            <imageLocation>polopoly-centos5-test-node/image-110125.manifest.xml</imageLocation>
            <imageState>available</imageState>
            <imageOwnerId>299230374258</imageOwnerId>
            <isPublic>false</isPublic>
            <architecture>x86_64</architecture>
            <imageType>machine</imageType>
            <kernelId>aki-550d2521</kernelId>
            <rootDeviceType>instance-store</rootDeviceType>
            <rootDeviceName>/dev/sda1</rootDeviceName>
            <blockDeviceMapping/>
            <virtualizationType>paravirtual</virtualizationType>
            <hypervisor>xen</hypervisor>
        </item>
        <item>
            <imageId>ami-3f3d174b</imageId>
            <imageLocation>polopoly-centos5-test-node/image-100531.manifest.xml</imageLocation>
            <imageState>available</imageState>
            <imageOwnerId>299230374258</imageOwnerId>
            <isPublic>false</isPublic>
            <architecture>x86_64</architecture>
            <imageType>machine</imageType>
            <kernelId>aki-550d2521</kernelId>
            <rootDeviceType>instance-store</rootDeviceType>
            <rootDeviceName>/dev/sda1</rootDeviceName>
            <blockDeviceMapping/>
            <virtualizationType>paravirtual</virtualizationType>
            <hypervisor>xen</hypervisor>
        </item>
        <item>
            <imageId>ami-422a0136</imageId>
            <imageLocation>polopoly-bigtest/ec2-front-20091027.manifest.xml</imageLocation>
            <imageState>available</imageState>
            <imageOwnerId>299230374258</imageOwnerId>
            <isPublic>false</isPublic>
            <architecture>x86_64</architecture>
            <imageType>machine</imageType>
            <rootDeviceType>instance-store</rootDeviceType>
            <blockDeviceMapping/>
            <virtualizationType>paravirtual</virtualizationType>
            <hypervisor>xen</hypervisor>
        </item>
        <item>
            <imageId>ami-43cee537</imageId>
            <imageLocation>polopoly-centos5-test-node/image-100118.manifest.xml</imageLocation>
            <imageState>available</imageState>
            <imageOwnerId>299230374258</imageOwnerId>
            <isPublic>false</isPublic>
            <architecture>x86_64</architecture>
            <imageType>machine</imageType>
            <kernelId>aki-550d2521</kernelId>
            <rootDeviceType>instance-store</rootDeviceType>
            <rootDeviceName>/dev/sda1</rootDeviceName>
            <blockDeviceMapping/>
            <virtualizationType>paravirtual</virtualizationType>
            <hypervisor>xen</hypervisor>
        </item>
        <item>
            <imageId>ami-4b3d173f</imageId>
            <imageLocation>polopoly-release-preview/image-100531-9-16-1-r56872.manifest.xml</imageLocation>
            <imageState>available</imageState>
            <imageOwnerId>299230374258</imageOwnerId>
            <isPublic>false</isPublic>
            <architecture>i386</architecture>
            <imageType>machine</imageType>
            <rootDeviceType>instance-store</rootDeviceType>
            <rootDeviceName>/dev/sda1</rootDeviceName>
            <blockDeviceMapping/>
            <virtualizationType>paravirtual</virtualizationType>
            <hypervisor>xen</hypervisor>
        </item>
        <item>
            <imageId>ami-4bdcf73f</imageId>
            <imageLocation>polopoly-centos5-test-node/image-100203.manifest.xml</imageLocation>
            <imageState>available</imageState>
            <imageOwnerId>299230374258</imageOwnerId>
            <isPublic>false</isPublic>
            <architecture>x86_64</architecture>
            <imageType>machine</imageType>
            <kernelId>aki-550d2521</kernelId>
            <rootDeviceType>instance-store</rootDeviceType>
            <rootDeviceName>/dev/sda1</rootDeviceName>
            <blockDeviceMapping/>
            <virtualizationType>paravirtual</virtualizationType>
            <hypervisor>xen</hypervisor>
        </item>
        <item>
            <imageId>ami-4dd9f239</imageId>
            <imageLocation>polopoly-bigtest/image-100129.manifest.xml</imageLocation>
            <imageState>available</imageState>
            <imageOwnerId>299230374258</imageOwnerId>
            <isPublic>false</isPublic>
            <architecture>x86_64</architecture>
            <imageType>machine</imageType>
            <rootDeviceType>instance-store</rootDeviceType>
            <rootDeviceName>/dev/sda1</rootDeviceName>
            <blockDeviceMapping/>
            <virtualizationType>paravirtual</virtualizationType>
            <hypervisor>xen</hypervisor>
        </item>
        <item>
            <imageId>ami-500e3b24</imageId>
            <imageLocation>299230374258/polopoly-centos5-test-node-ebs-101115-4</imageLocation>
            <imageState>available</imageState>
            <imageOwnerId>299230374258</imageOwnerId>
            <isPublic>false</isPublic>
            <architecture>x86_64</architecture>
            <imageType>machine</imageType>
            <name>polopoly-centos5-test-node-ebs-101115-4</name>
            <rootDeviceType>ebs</rootDeviceType>
            <rootDeviceName>/dev/sda1</rootDeviceName>
            <blockDeviceMapping>
                <item>
                    <deviceName>/dev/sda1</deviceName>
                    <ebs>
                        <snapshotId>snap-5814aa31</snapshotId>
                        <volumeSize>20</volumeSize>
                        <deleteOnTermination>true</deleteOnTermination>
                    </ebs>
                </item>
            </blockDeviceMapping>
            <virtualizationType>paravirtual</virtualizationType>
            <hypervisor>xen</hypervisor>
        </item>
        <item>
            <imageId>ami-50b29824</imageId>
            <imageLocation>polopoly-release-preview/image-100830-9-17-DR4-r57473.manifest.xml</imageLocation>
            <imageState>available</imageState>
            <imageOwnerId>299230374258</imageOwnerId>
            <isPublic>false</isPublic>
            <architecture>i386</architecture>
            <imageType>machine</imageType>
            <rootDeviceType>instance-store</rootDeviceType>
            <rootDeviceName>/dev/sda1</rootDeviceName>
            <blockDeviceMapping/>
            <virtualizationType>paravirtual</virtualizationType>
            <hypervisor>xen</hypervisor>
        </item>
        <item>
            <imageId>ami-516b4125</imageId>
            <imageLocation>polopoly-centos5-test-node/image-100330.manifest.xml</imageLocation>
            <imageState>available</imageState>
            <imageOwnerId>299230374258</imageOwnerId>
            <isPublic>false</isPublic>
            <architecture>x86_64</architecture>
            <imageType>machine</imageType>
            <kernelId>aki-550d2521</kernelId>
            <rootDeviceType>instance-store</rootDeviceType>
            <rootDeviceName>/dev/sda1</rootDeviceName>
            <blockDeviceMapping/>
            <virtualizationType>paravirtual</virtualizationType>
            <hypervisor>xen</hypervisor>
        </item>
        <item>
            <imageId>ami-5924102d</imageId>
            <imageLocation>polopoly-centos5-test-node/image-110126.manifest.xml</imageLocation>
            <imageState>available</imageState>
            <imageOwnerId>299230374258</imageOwnerId>
            <isPublic>false</isPublic>
            <architecture>x86_64</architecture>
            <imageType>machine</imageType>
            <kernelId>aki-550d2521</kernelId>
            <rootDeviceType>instance-store</rootDeviceType>
            <rootDeviceName>/dev/sda1</rootDeviceName>
            <blockDeviceMapping/>
            <virtualizationType>paravirtual</virtualizationType>
            <hypervisor>xen</hypervisor>
        </item>
        <item>
            <imageId>ami-5d341f29</imageId>
            <imageLocation>polopoly-bigtest/image-091120-jmeter.manifest.xml</imageLocation>
            <imageState>available</imageState>
            <imageOwnerId>299230374258</imageOwnerId>
            <isPublic>false</isPublic>
            <architecture>i386</architecture>
            <imageType>machine</imageType>
            <rootDeviceType>instance-store</rootDeviceType>
            <blockDeviceMapping/>
            <virtualizationType>paravirtual</virtualizationType>
            <hypervisor>xen</hypervisor>
        </item>
        <item>
            <imageId>ami-5f341f2b</imageId>
            <imageLocation>polopoly-bigtest/image-091120.manifest.xml</imageLocation>
            <imageState>available</imageState>
            <imageOwnerId>299230374258</imageOwnerId>
            <isPublic>false</isPublic>
            <architecture>x86_64</architecture>
            <imageType>machine</imageType>
            <rootDeviceType>instance-store</rootDeviceType>
            <blockDeviceMapping/>
            <virtualizationType>paravirtual</virtualizationType>
            <hypervisor>xen</hypervisor>
        </item>
        <item>
            <imageId>ami-62685d16</imageId>
            <imageLocation>polopoly-release-preview/image-101001-9-17-DR7-0beb877.manifest.xml</imageLocation>
            <imageState>available</imageState>
            <imageOwnerId>299230374258</imageOwnerId>
            <isPublic>false</isPublic>
            <architecture>i386</architecture>
            <imageType>machine</imageType>
            <rootDeviceType>instance-store</rootDeviceType>
            <rootDeviceName>/dev/sda1</rootDeviceName>
            <blockDeviceMapping/>
            <virtualizationType>paravirtual</virtualizationType>
            <hypervisor>xen</hypervisor>
        </item>
        <item>
            <imageId>ami-65efda11</imageId>
            <imageLocation>polopoly-centos5-test-node/image-101129.manifest.xml</imageLocation>
            <imageState>available</imageState>
            <imageOwnerId>299230374258</imageOwnerId>
            <isPublic>false</isPublic>
            <architecture>x86_64</architecture>
            <imageType>machine</imageType>
            <kernelId>aki-550d2521</kernelId>
            <rootDeviceType>instance-store</rootDeviceType>
            <rootDeviceName>/dev/sda1</rootDeviceName>
            <blockDeviceMapping/>
            <virtualizationType>paravirtual</virtualizationType>
            <hypervisor>xen</hypervisor>
        </item>
        <item>
            <imageId>ami-66457012</imageId>
            <imageLocation>polopoly-centos5-test-node/image-101012.manifest.xml</imageLocation>
            <imageState>available</imageState>
            <imageOwnerId>299230374258</imageOwnerId>
            <isPublic>false</isPublic>
            <architecture>x86_64</architecture>
            <imageType>machine</imageType>
            <kernelId>aki-550d2521</kernelId>
            <rootDeviceType>instance-store</rootDeviceType>
            <rootDeviceName>/dev/sda1</rootDeviceName>
            <blockDeviceMapping/>
            <virtualizationType>paravirtual</virtualizationType>
            <hypervisor>xen</hypervisor>
        </item>
        <item>
            <imageId>ami-69bb901d</imageId>
            <imageLocation>polopoly-centos5-test-node/image-100222.manifest.xml</imageLocation>
            <imageState>available</imageState>
            <imageOwnerId>299230374258</imageOwnerId>
            <isPublic>false</isPublic>
            <architecture>x86_64</architecture>
            <imageType>machine</imageType>
            <kernelId>aki-550d2521</kernelId>
            <rootDeviceType>instance-store</rootDeviceType>
            <rootDeviceName>/dev/sda1</rootDeviceName>
            <blockDeviceMapping/>
            <virtualizationType>paravirtual</virtualizationType>
            <hypervisor>xen</hypervisor>
        </item>
        <item>
            <imageId>ami-69e0d51d</imageId>
            <imageLocation>polopoly-centos5-test-node/image-101126.manifest.xml</imageLocation>
            <imageState>available</imageState>
            <imageOwnerId>299230374258</imageOwnerId>
            <isPublic>false</isPublic>
            <architecture>x86_64</architecture>
            <imageType>machine</imageType>
            <kernelId>aki-550d2521</kernelId>
            <rootDeviceType>instance-store</rootDeviceType>
            <rootDeviceName>/dev/sda1</rootDeviceName>
            <blockDeviceMapping/>
            <virtualizationType>paravirtual</virtualizationType>
            <hypervisor>xen</hypervisor>
        </item>
        <item>
            <imageId>ami-6dc7ec19</imageId>
            <imageLocation>polopoly-centos5-main-node/image-100124.manifest.xml</imageLocation>
            <imageState>available</imageState>
            <imageOwnerId>299230374258</imageOwnerId>
            <isPublic>false</isPublic>
            <architecture>i386</architecture>
            <imageType>machine</imageType>
            <rootDeviceType>instance-store</rootDeviceType>
            <rootDeviceName>/dev/sda1</rootDeviceName>
            <blockDeviceMapping/>
            <virtualizationType>paravirtual</virtualizationType>
            <hypervisor>xen</hypervisor>
        </item>
        <item>
            <imageId>ami-6fecc61b</imageId>
            <imageLocation>polopoly-centos5-test-node/image-100702.manifest.xml</imageLocation>
            <imageState>available</imageState>
            <imageOwnerId>299230374258</imageOwnerId>
            <isPublic>false</isPublic>
            <architecture>x86_64</architecture>
            <imageType>machine</imageType>
            <kernelId>aki-550d2521</kernelId>
            <rootDeviceType>instance-store</rootDeviceType>
            <rootDeviceName>/dev/sda1</rootDeviceName>
            <blockDeviceMapping/>
            <virtualizationType>paravirtual</virtualizationType>
            <hypervisor>xen</hypervisor>
        </item>
        <item>
            <imageId>ami-71e5d005</imageId>
            <imageLocation>polopoly-centos5-test-node/image-101124.manifest.xml</imageLocation>
            <imageState>available</imageState>
            <imageOwnerId>299230374258</imageOwnerId>
            <isPublic>false</isPublic>
            <architecture>x86_64</architecture>
            <imageType>machine</imageType>
            <kernelId>aki-550d2521</kernelId>
            <rootDeviceType>instance-store</rootDeviceType>
            <rootDeviceName>/dev/sda1</rootDeviceName>
            <blockDeviceMapping/>
            <virtualizationType>paravirtual</virtualizationType>
            <hypervisor>xen</hypervisor>
        </item>
        <item>
            <imageId>ami-72635606</imageId>
            <imageLocation>polopoly-centos5-test-node/image-100928.manifest.xml</imageLocation>
            <imageState>available</imageState>
            <imageOwnerId>299230374258</imageOwnerId>
            <isPublic>false</isPublic>
            <architecture>x86_64</architecture>
            <imageType>machine</imageType>
            <kernelId>aki-550d2521</kernelId>
            <rootDeviceType>instance-store</rootDeviceType>
            <rootDeviceName>/dev/sda1</rootDeviceName>
            <blockDeviceMapping/>
            <virtualizationType>paravirtual</virtualizationType>
            <hypervisor>xen</hypervisor>
        </item>
        <item>
            <imageId>ami-76685d02</imageId>
            <imageLocation>polopoly-release-preview/image-20101001.manifest.xml</imageLocation>
            <imageState>available</imageState>
            <imageOwnerId>299230374258</imageOwnerId>
            <isPublic>false</isPublic>
            <architecture>i386</architecture>
            <imageType>machine</imageType>
            <rootDeviceType>instance-store</rootDeviceType>
            <rootDeviceName>/dev/sda1</rootDeviceName>
            <blockDeviceMapping/>
            <virtualizationType>paravirtual</virtualizationType>
            <hypervisor>xen</hypervisor>
        </item>
        <item>
            <imageId>ami-7dbb9009</imageId>
            <imageLocation>polopoly-centos5-main-node/image.manifest.xml</imageLocation>
            <imageState>available</imageState>
            <imageOwnerId>299230374258</imageOwnerId>
            <isPublic>false</isPublic>
            <architecture>i386</architecture>
            <imageType>machine</imageType>
            <rootDeviceType>instance-store</rootDeviceType>
            <rootDeviceName>/dev/sda1</rootDeviceName>
            <blockDeviceMapping/>
            <virtualizationType>paravirtual</virtualizationType>
            <hypervisor>xen</hypervisor>
        </item>
        <item>
            <imageId>ami-82ffcaf6</imageId>
            <imageLocation>polopoly-release-preview/image-101122-9-17-DR7-r58191.manifest.xml</imageLocation>
            <imageState>available</imageState>
            <imageOwnerId>299230374258</imageOwnerId>
            <isPublic>false</isPublic>
            <architecture>i386</architecture>
            <imageType>machine</imageType>
            <rootDeviceType>instance-store</rootDeviceType>
            <rootDeviceName>/dev/sda1</rootDeviceName>
            <blockDeviceMapping/>
            <virtualizationType>paravirtual</virtualizationType>
            <hypervisor>xen</hypervisor>
        </item>
        <item>
            <imageId>ami-8ba590ff</imageId>
            <imageLocation>polopoly-release-preview/image-101220-9-17-DR8-r58372.manifest.xml</imageLocation>
            <imageState>available</imageState>
            <imageOwnerId>299230374258</imageOwnerId>
            <isPublic>false</isPublic>
            <architecture>i386</architecture>
            <imageType>machine</imageType>
            <rootDeviceType>instance-store</rootDeviceType>
            <rootDeviceName>/dev/sda1</rootDeviceName>
            <blockDeviceMapping/>
            <virtualizationType>paravirtual</virtualizationType>
            <hypervisor>xen</hypervisor>
        </item>
        <item>
            <imageId>ami-8fdaeffb</imageId>
            <imageLocation>polopoly-centos5-test-node/image-101207.manifest.xml</imageLocation>
            <imageState>available</imageState>
            <imageOwnerId>299230374258</imageOwnerId>
            <isPublic>false</isPublic>
            <architecture>x86_64</architecture>
            <imageType>machine</imageType>
            <kernelId>aki-550d2521</kernelId>
            <rootDeviceType>instance-store</rootDeviceType>
            <rootDeviceName>/dev/sda1</rootDeviceName>
            <blockDeviceMapping/>
            <virtualizationType>paravirtual</virtualizationType>
            <hypervisor>xen</hypervisor>
        </item>
        <item>
            <imageId>ami-911b30e5</imageId>
            <imageLocation>polopoly-release-preview/image-091201-9-15-DR1-r55697.manifest.xml</imageLocation>
            <imageState>available</imageState>
            <imageOwnerId>299230374258</imageOwnerId>
            <isPublic>false</isPublic>
            <architecture>i386</architecture>
            <imageType>machine</imageType>
            <rootDeviceType>instance-store</rootDeviceType>
            <rootDeviceName>/dev/sda1</rootDeviceName>
            <blockDeviceMapping/>
            <virtualizationType>paravirtual</virtualizationType>
            <hypervisor>xen</hypervisor>
        </item>
        <item>
            <imageId>ami-945873e0</imageId>
            <imageLocation>polopoly-release-preview/image-091015-9-15-DR1-r55204.manifest.xml</imageLocation>
            <imageState>available</imageState>
            <imageOwnerId>299230374258</imageOwnerId>
            <isPublic>false</isPublic>
            <architecture>i386</architecture>
            <imageType>machine</imageType>
            <rootDeviceType>instance-store</rootDeviceType>
            <blockDeviceMapping/>
            <virtualizationType>paravirtual</virtualizationType>
            <hypervisor>xen</hypervisor>
        </item>
        <item>
            <imageId>ami-95def5e1</imageId>
            <imageLocation>polopoly-release-preview/image-100202-9-15-DR3-r56049.manifest.xml</imageLocation>
            <imageState>available</imageState>
            <imageOwnerId>299230374258</imageOwnerId>
            <isPublic>false</isPublic>
            <architecture>i386</architecture>
            <imageType>machine</imageType>
            <rootDeviceType>instance-store</rootDeviceType>
            <rootDeviceName>/dev/sda1</rootDeviceName>
            <blockDeviceMapping/>
            <virtualizationType>paravirtual</virtualizationType>
            <hypervisor>xen</hypervisor>
        </item>
        <item>
            <imageId>ami-9b1024ef</imageId>
            <imageLocation>polopoly-centos5-test-node/image-110201.manifest.xml</imageLocation>
            <imageState>available</imageState>
            <imageOwnerId>299230374258</imageOwnerId>
            <isPublic>false</isPublic>
            <architecture>x86_64</architecture>
            <imageType>machine</imageType>
            <kernelId>aki-550d2521</kernelId>
            <rootDeviceType>instance-store</rootDeviceType>
            <rootDeviceName>/dev/sda1</rootDeviceName>
            <blockDeviceMapping/>
            <virtualizationType>paravirtual</virtualizationType>
            <hypervisor>xen</hypervisor>
        </item>
        <item>
            <imageId>ami-9f9eb5eb</imageId>
            <imageLocation>polopoly-centos5-test-node/image-100322.manifest.xml</imageLocation>
            <imageState>available</imageState>
            <imageOwnerId>299230374258</imageOwnerId>
            <isPublic>false</isPublic>
            <architecture>x86_64</architecture>
            <imageType>machine</imageType>
            <kernelId>aki-550d2521</kernelId>
            <rootDeviceType>instance-store</rootDeviceType>
            <rootDeviceName>/dev/sda1</rootDeviceName>
            <blockDeviceMapping/>
            <virtualizationType>paravirtual</virtualizationType>
            <hypervisor>xen</hypervisor>
        </item>
        <item>
            <imageId>ami-b4755ec0</imageId>
            <imageLocation>polopoly-centos5-test-node/image-090826.manifest.xml</imageLocation>
            <imageState>available</imageState>
            <imageOwnerId>299230374258</imageOwnerId>
            <isPublic>false</isPublic>
            <architecture>x86_64</architecture>
            <imageType>machine</imageType>
            <kernelId>aki-550d2521</kernelId>
            <rootDeviceType>instance-store</rootDeviceType>
            <blockDeviceMapping/>
            <virtualizationType>paravirtual</virtualizationType>
            <hypervisor>xen</hypervisor>
        </item>
        <item>
            <imageId>ami-b6755ec2</imageId>
            <imageLocation>polopoly-centos5-temis-node/image-090826.manifest.xml</imageLocation>
            <imageState>available</imageState>
            <imageOwnerId>299230374258</imageOwnerId>
            <isPublic>false</isPublic>
            <architecture>i386</architecture>
            <imageType>machine</imageType>
            <rootDeviceType>instance-store</rootDeviceType>
            <blockDeviceMapping/>
            <virtualizationType>paravirtual</virtualizationType>
            <hypervisor>xen</hypervisor>
        </item>
        <item>
            <imageId>ami-be586dca</imageId>
            <imageLocation>polopoly-release-preview/image-101011-9-17-DR7-r57815.manifest.xml</imageLocation>
            <imageState>available</imageState>
            <imageOwnerId>299230374258</imageOwnerId>
            <isPublic>false</isPublic>
            <architecture>i386</architecture>
            <imageType>machine</imageType>
            <rootDeviceType>instance-store</rootDeviceType>
            <rootDeviceName>/dev/sda1</rootDeviceName>
            <blockDeviceMapping/>
            <virtualizationType>paravirtual</virtualizationType>
            <hypervisor>xen</hypervisor>
        </item>
        <item>
            <imageId>ami-c02803b4</imageId>
            <imageLocation>polopoly-bigtest/ec2-front-091029.manifest.xml</imageLocation>
            <imageState>available</imageState>
            <imageOwnerId>299230374258</imageOwnerId>
            <isPublic>false</isPublic>
            <architecture>x86_64</architecture>
            <imageType>machine</imageType>
            <rootDeviceType>instance-store</rootDeviceType>
            <blockDeviceMapping/>
            <virtualizationType>paravirtual</virtualizationType>
            <hypervisor>xen</hypervisor>
        </item>
        <item>
            <imageId>ami-c64e7bb2</imageId>
            <imageLocation>polopoly-oracle/oracle11-101019-2.manifest.xml</imageLocation>
            <imageState>available</imageState>
            <imageOwnerId>299230374258</imageOwnerId>
            <isPublic>false</isPublic>
            <architecture>x86_64</architecture>
            <imageType>machine</imageType>
            <kernelId>aki-3190bb45</kernelId>
            <ramdiskId>ari-3790bb43</ramdiskId>
            <rootDeviceType>instance-store</rootDeviceType>
            <blockDeviceMapping/>
            <virtualizationType>paravirtual</virtualizationType>
            <hypervisor>xen</hypervisor>
        </item>
        <item>
            <imageId>ami-c65f74b2</imageId>
            <imageLocation>polopoly-centos5-preview-template-node/image-091016.manifest.xml</imageLocation>
            <imageState>available</imageState>
            <imageOwnerId>299230374258</imageOwnerId>
            <isPublic>false</isPublic>
            <architecture>i386</architecture>
            <imageType>machine</imageType>
            <rootDeviceType>instance-store</rootDeviceType>
            <blockDeviceMapping/>
            <virtualizationType>paravirtual</virtualizationType>
            <hypervisor>xen</hypervisor>
        </item>
        <item>
            <imageId>ami-c86055bc</imageId>
            <imageLocation>polopoly-release-preview/image-100928-9-17-DR5-r57689.manifest.xml</imageLocation>
            <imageState>available</imageState>
            <imageOwnerId>299230374258</imageOwnerId>
            <isPublic>false</isPublic>
            <architecture>i386</architecture>
            <imageType>machine</imageType>
            <rootDeviceType>instance-store</rootDeviceType>
            <rootDeviceName>/dev/sda1</rootDeviceName>
            <blockDeviceMapping/>
            <virtualizationType>paravirtual</virtualizationType>
            <hypervisor>xen</hypervisor>
        </item>
        <item>
            <imageId>ami-cb8ea5bf</imageId>
            <imageLocation>polopoly-centos5-test-node/image-100310.manifest.xml</imageLocation>
            <imageState>available</imageState>
            <imageOwnerId>299230374258</imageOwnerId>
            <isPublic>false</isPublic>
            <architecture>x86_64</architecture>
            <imageType>machine</imageType>
            <kernelId>aki-550d2521</kernelId>
            <rootDeviceType>instance-store</rootDeviceType>
            <rootDeviceName>/dev/sda1</rootDeviceName>
            <blockDeviceMapping/>
            <virtualizationType>paravirtual</virtualizationType>
            <hypervisor>xen</hypervisor>
        </item>
        <item>
            <imageId>ami-d02e05a4</imageId>
            <imageLocation>polopoly-release-preview/image-091102-9-15-DR1-r55443.manifest.xml</imageLocation>
            <imageState>available</imageState>
            <imageOwnerId>299230374258</imageOwnerId>
            <isPublic>false</isPublic>
            <architecture>i386</architecture>
            <imageType>machine</imageType>
            <rootDeviceType>instance-store</rootDeviceType>
            <blockDeviceMapping/>
            <virtualizationType>paravirtual</virtualizationType>
            <hypervisor>xen</hypervisor>
        </item>
        <item>
            <imageId>ami-d1dff4a5</imageId>
            <imageLocation>polopoly-release-preview/image-100201-9-15-DR3-r56038.manifest.xml</imageLocation>
            <imageState>available</imageState>
            <imageOwnerId>299230374258</imageOwnerId>
            <isPublic>false</isPublic>
            <architecture>i386</architecture>
            <imageType>machine</imageType>
            <rootDeviceType>instance-store</rootDeviceType>
            <rootDeviceName>/dev/sda1</rootDeviceName>
            <blockDeviceMapping/>
            <virtualizationType>paravirtual</virtualizationType>
            <hypervisor>xen</hypervisor>
        </item>
        <item>
            <imageId>ami-d3b992a7</imageId>
            <imageLocation>polopoly-centos5-test-node/image-100224.manifest.xml</imageLocation>
            <imageState>available</imageState>
            <imageOwnerId>299230374258</imageOwnerId>
            <isPublic>false</isPublic>
            <architecture>x86_64</architecture>
            <imageType>machine</imageType>
            <kernelId>aki-550d2521</kernelId>
            <rootDeviceType>instance-store</rootDeviceType>
            <rootDeviceName>/dev/sda1</rootDeviceName>
            <blockDeviceMapping/>
            <virtualizationType>paravirtual</virtualizationType>
            <hypervisor>xen</hypervisor>
        </item>
        <item>
            <imageId>ami-d4765da0</imageId>
            <imageLocation>polopoly-centos5-main-node/image-090826.manifest.xml</imageLocation>
            <imageState>available</imageState>
            <imageOwnerId>299230374258</imageOwnerId>
            <isPublic>false</isPublic>
            <architecture>i386</architecture>
            <imageType>machine</imageType>
            <rootDeviceType>instance-store</rootDeviceType>
            <blockDeviceMapping/>
            <virtualizationType>paravirtual</virtualizationType>
            <hypervisor>xen</hypervisor>
        </item>
        <item>
            <imageId>ami-d96e44ad</imageId>
            <imageLocation>polopoly-centos5-test-node/image-100401.manifest.xml</imageLocation>
            <imageState>available</imageState>
            <imageOwnerId>299230374258</imageOwnerId>
            <isPublic>false</isPublic>
            <architecture>x86_64</architecture>
            <imageType>machine</imageType>
            <kernelId>aki-550d2521</kernelId>
            <rootDeviceType>instance-store</rootDeviceType>
            <rootDeviceName>/dev/sda1</rootDeviceName>
            <blockDeviceMapping/>
            <virtualizationType>paravirtual</virtualizationType>
            <hypervisor>xen</hypervisor>
        </item>
        <item>
            <imageId>ami-d99ab1ad</imageId>
            <imageLocation>polopoly-centos5-test-node/image-100318.manifest.xml</imageLocation>
            <imageState>available</imageState>
            <imageOwnerId>299230374258</imageOwnerId>
            <isPublic>false</isPublic>
            <architecture>x86_64</architecture>
            <imageType>machine</imageType>
            <kernelId>aki-550d2521</kernelId>
            <rootDeviceType>instance-store</rootDeviceType>
            <rootDeviceName>/dev/sda1</rootDeviceName>
            <blockDeviceMapping/>
            <virtualizationType>paravirtual</virtualizationType>
            <hypervisor>xen</hypervisor>
        </item>
        <item>
            <imageId>ami-db2511af</imageId>
            <imageLocation>polopoly-centos5-test-node/image-110126-2.manifest.xml</imageLocation>
            <imageState>available</imageState>
            <imageOwnerId>299230374258</imageOwnerId>
            <isPublic>false</isPublic>
            <architecture>x86_64</architecture>
            <imageType>machine</imageType>
            <kernelId>aki-550d2521</kernelId>
            <rootDeviceType>instance-store</rootDeviceType>
            <rootDeviceName>/dev/sda1</rootDeviceName>
            <blockDeviceMapping/>
            <virtualizationType>paravirtual</virtualizationType>
            <hypervisor>xen</hypervisor>
        </item>
        <item>
            <imageId>ami-dd8ca7a9</imageId>
            <imageLocation>releng-9-9-centos5-test-node/image-100310.manifest.xml</imageLocation>
            <imageState>available</imageState>
            <imageOwnerId>299230374258</imageOwnerId>
            <isPublic>false</isPublic>
            <architecture>x86_64</architecture>
            <imageType>machine</imageType>
            <kernelId>aki-550d2521</kernelId>
            <rootDeviceType>instance-store</rootDeviceType>
            <rootDeviceName>/dev/sda1</rootDeviceName>
            <blockDeviceMapping/>
            <virtualizationType>paravirtual</virtualizationType>
            <hypervisor>xen</hypervisor>
        </item>
        <item>
            <imageId>ami-e1b09b95</imageId>
            <imageLocation>polopoly-centos5-test-node/image-100303.manifest.xml</imageLocation>
            <imageState>available</imageState>
            <imageOwnerId>299230374258</imageOwnerId>
            <isPublic>false</isPublic>
            <architecture>x86_64</architecture>
            <imageType>machine</imageType>
            <kernelId>aki-550d2521</kernelId>
            <rootDeviceType>instance-store</rootDeviceType>
            <rootDeviceName>/dev/sda1</rootDeviceName>
            <blockDeviceMapping/>
            <virtualizationType>paravirtual</virtualizationType>
            <hypervisor>xen</hypervisor>
        </item>
        <item>
            <imageId>ami-e4330690</imageId>
            <imageLocation>polopoly-bigtest/image-101025.manifest.xml</imageLocation>
            <imageState>available</imageState>
            <imageOwnerId>299230374258</imageOwnerId>
            <isPublic>false</isPublic>
            <architecture>x86_64</architecture>
            <imageType>machine</imageType>
            <rootDeviceType>instance-store</rootDeviceType>
            <rootDeviceName>/dev/sda1</rootDeviceName>
            <blockDeviceMapping/>
            <virtualizationType>paravirtual</virtualizationType>
            <hypervisor>xen</hypervisor>
        </item>
        <item>
            <imageId>ami-e4457090</imageId>
            <imageLocation>polopoly-centos5-test-node/image-101012-3.manifest.xml</imageLocation>
            <imageState>available</imageState>
            <imageOwnerId>299230374258</imageOwnerId>
            <isPublic>false</isPublic>
            <architecture>x86_64</architecture>
            <imageType>machine</imageType>
            <kernelId>aki-550d2521</kernelId>
            <rootDeviceType>instance-store</rootDeviceType>
            <rootDeviceName>/dev/sda1</rootDeviceName>
            <blockDeviceMapping/>
            <virtualizationType>paravirtual</virtualizationType>
            <hypervisor>xen</hypervisor>
        </item>
        <item>
            <imageId>ami-e4d6fc90</imageId>
            <imageLocation>polopoly-centos5-test-node/image-100810.manifest.xml</imageLocation>
            <imageState>available</imageState>
            <imageOwnerId>299230374258</imageOwnerId>
            <isPublic>false</isPublic>
            <architecture>x86_64</architecture>
            <imageType>machine</imageType>
            <kernelId>aki-550d2521</kernelId>
            <rootDeviceType>instance-store</rootDeviceType>
            <rootDeviceName>/dev/sda1</rootDeviceName>
            <blockDeviceMapping/>
            <virtualizationType>paravirtual</virtualizationType>
            <hypervisor>xen</hypervisor>
        </item>
        <item>
            <imageId>ami-ec516498</imageId>
            <imageLocation>polopoly-centos5-test-node/image-101006.manifest.xml</imageLocation>
            <imageState>available</imageState>
            <imageOwnerId>299230374258</imageOwnerId>
            <isPublic>false</isPublic>
            <architecture>x86_64</architecture>
            <imageType>machine</imageType>
            <kernelId>aki-550d2521</kernelId>
            <rootDeviceType>instance-store</rootDeviceType>
            <rootDeviceName>/dev/sda1</rootDeviceName>
            <blockDeviceMapping/>
            <virtualizationType>paravirtual</virtualizationType>
            <hypervisor>xen</hypervisor>
        </item>
        <item>
            <imageId>ami-edb39899</imageId>
            <imageLocation>polopoly-centos5-test-node/image-100301.manifest.xml</imageLocation>
            <imageState>available</imageState>
            <imageOwnerId>299230374258</imageOwnerId>
            <isPublic>false</isPublic>
            <architecture>x86_64</architecture>
            <imageType>machine</imageType>
            <kernelId>aki-550d2521</kernelId>
            <rootDeviceType>instance-store</rootDeviceType>
            <rootDeviceName>/dev/sda1</rootDeviceName>
            <blockDeviceMapping/>
            <virtualizationType>paravirtual</virtualizationType>
            <hypervisor>xen</hypervisor>
        </item>
        <item>
            <imageId>ami-ee3d089a</imageId>
            <imageLocation>polopoly-release-preview/image-101026-9-17-DR6-r57930.manifest.xml</imageLocation>
            <imageState>available</imageState>
            <imageOwnerId>299230374258</imageOwnerId>
            <isPublic>false</isPublic>
            <architecture>i386</architecture>
            <imageType>machine</imageType>
            <rootDeviceType>instance-store</rootDeviceType>
            <rootDeviceName>/dev/sda1</rootDeviceName>
            <blockDeviceMapping/>
            <virtualizationType>paravirtual</virtualizationType>
            <hypervisor>xen</hypervisor>
        </item>
        <item>
            <imageId>ami-efd9f29b</imageId>
            <imageLocation>polopoly-bigtest/image-100129B.manifest.xml</imageLocation>
            <imageState>available</imageState>
            <imageOwnerId>299230374258</imageOwnerId>
            <isPublic>false</isPublic>
            <architecture>x86_64</architecture>
            <imageType>machine</imageType>
            <rootDeviceType>instance-store</rootDeviceType>
            <rootDeviceName>/dev/sda1</rootDeviceName>
            <blockDeviceMapping/>
            <virtualizationType>paravirtual</virtualizationType>
            <hypervisor>xen</hypervisor>
        </item>
        <item>
            <imageId>ami-efeac09b</imageId>
            <imageLocation>polopoly-centos5-test-node/image-100628.manifest.xml</imageLocation>
            <imageState>available</imageState>
            <imageOwnerId>299230374258</imageOwnerId>
            <isPublic>false</isPublic>
            <architecture>x86_64</architecture>
            <imageType>machine</imageType>
            <kernelId>aki-550d2521</kernelId>
            <rootDeviceType>instance-store</rootDeviceType>
            <rootDeviceName>/dev/sda1</rootDeviceName>
            <blockDeviceMapping/>
            <virtualizationType>paravirtual</virtualizationType>
            <hypervisor>xen</hypervisor>
        </item>
        <item>
            <imageId>ami-f20e3b86</imageId>
            <imageLocation>299230374258/az-20g-image</imageLocation>
            <imageState>available</imageState>
            <imageOwnerId>299230374258</imageOwnerId>
            <isPublic>false</isPublic>
            <architecture>x86_64</architecture>
            <imageType>machine</imageType>
            <kernelId>aki-4feec43b</kernelId>
            <name>az-20g-image</name>
            <rootDeviceType>ebs</rootDeviceType>
            <rootDeviceName>/dev/sda1</rootDeviceName>
            <blockDeviceMapping>
                <item>
                    <deviceName>/dev/sda1</deviceName>
                    <ebs>
                        <snapshotId>snap-5e0cb237</snapshotId>
                        <volumeSize>20</volumeSize>
                        <deleteOnTermination>false</deleteOnTermination>
                    </ebs>
                </item>
            </blockDeviceMapping>
            <virtualizationType>paravirtual</virtualizationType>
            <hypervisor>xen</hypervisor>
        </item>
        <item>
            <imageId>ami-f4497c80</imageId>
            <imageLocation>polopoly-release-preview/image-101019-9-17-DR7-r57885.manifest.xml</imageLocation>
            <imageState>available</imageState>
            <imageOwnerId>299230374258</imageOwnerId>
            <isPublic>false</isPublic>
            <architecture>i386</architecture>
            <imageType>machine</imageType>
            <rootDeviceType>instance-store</rootDeviceType>
            <rootDeviceName>/dev/sda1</rootDeviceName>
            <blockDeviceMapping/>
            <virtualizationType>paravirtual</virtualizationType>
            <hypervisor>xen</hypervisor>
        </item>
        <item>
            <imageId>ami-f44a6180</imageId>
            <imageLocation>polopoly-windows2003-test-node/image-090826.manifest.xml</imageLocation>
            <imageState>available</imageState>
            <imageOwnerId>299230374258</imageOwnerId>
            <isPublic>false</isPublic>
            <architecture>x86_64</architecture>
            <imageType>machine</imageType>
            <platform>windows</platform>
            <rootDeviceType>instance-store</rootDeviceType>
            <blockDeviceMapping/>
            <virtualizationType>hvm</virtualizationType>
            <hypervisor>xen</hypervisor>
        </item>
        <item>
            <imageId>ami-f66c5982</imageId>
            <imageLocation>polopoly-release-preview/image-100930-9-17-DR7-0beb877.manifest.xml</imageLocation>
            <imageState>available</imageState>
            <imageOwnerId>299230374258</imageOwnerId>
            <isPublic>false</isPublic>
            <architecture>i386</architecture>
            <imageType>machine</imageType>
            <rootDeviceType>instance-store</rootDeviceType>
            <rootDeviceName>/dev/sda1</rootDeviceName>
            <blockDeviceMapping/>
            <virtualizationType>paravirtual</virtualizationType>
            <hypervisor>xen</hypervisor>
        </item>
        <item>
            <imageId>ami-f7d3e683</imageId>
            <imageLocation>polopoly-centos5-test-node/image-101203.manifest.xml</imageLocation>
            <imageState>available</imageState>
            <imageOwnerId>299230374258</imageOwnerId>
            <isPublic>false</isPublic>
            <architecture>x86_64</architecture>
            <imageType>machine</imageType>
            <kernelId>aki-550d2521</kernelId>
            <rootDeviceType>instance-store</rootDeviceType>
            <rootDeviceName>/dev/sda1</rootDeviceName>
            <blockDeviceMapping/>
            <virtualizationType>paravirtual</virtualizationType>
            <hypervisor>xen</hypervisor>
        </item>
        <item>
            <imageId>ami-f82a018c</imageId>
            <imageLocation>polopoly-bigtest/ec2-front-20091028.2.manifest.xml</imageLocation>
            <imageState>available</imageState>
            <imageOwnerId>299230374258</imageOwnerId>
            <isPublic>false</isPublic>
            <architecture>x86_64</architecture>
            <imageType>machine</imageType>
            <rootDeviceType>instance-store</rootDeviceType>
            <blockDeviceMapping/>
            <virtualizationType>paravirtual</virtualizationType>
            <hypervisor>xen</hypervisor>
        </item>
        <item>
            <imageId>ami-f85b6e8c</imageId>
            <imageLocation>polopoly-release-preview/image-101011-9-17-DR7-Minutely-RELENG-9-17-DR7-453.manifest.xml</imageLocation>
            <imageState>available</imageState>
            <imageOwnerId>299230374258</imageOwnerId>
            <isPublic>false</isPublic>
            <architecture>i386</architecture>
            <imageType>machine</imageType>
            <rootDeviceType>instance-store</rootDeviceType>
            <rootDeviceName>/dev/sda1</rootDeviceName>
            <blockDeviceMapping/>
            <virtualizationType>paravirtual</virtualizationType>
            <hypervisor>xen</hypervisor>
        </item>
        <item>
            <imageId>ami-f86f5a8c</imageId>
            <imageLocation>polopoly-release-preview/image-100930-9-17-DR5-r57689.manifest.xml</imageLocation>
            <imageState>available</imageState>
            <imageOwnerId>299230374258</imageOwnerId>
            <isPublic>false</isPublic>
            <architecture>i386</architecture>
            <imageType>machine</imageType>
            <rootDeviceType>instance-store</rootDeviceType>
            <rootDeviceName>/dev/sda1</rootDeviceName>
            <blockDeviceMapping/>
            <virtualizationType>paravirtual</virtualizationType>
            <hypervisor>xen</hypervisor>
        </item>
    </imagesSet>
</DescribeImagesResponse>